<?xml version="1.0" encoding="UTF-8"?>
<wnd xmlns="http://www.asoft.ru/xsl/ai" id="GateValvesAdd" class="generic" title="`Задвижки`">
  <a id="Choose_Producer">
    <evt aid="popupcall" type="WM_POPUP" id="Choose_Producer" src="/act/GPN/ProducerListPopup" args="" rets=""/>
  </a>
  <a id="Choose_Shipper">
    <evt aid="popupcall" type="WM_POPUP" id="Choose_Shipper" src="/act/GPN/ShipperListPopup" args="" rets=""/>
  </a>
  <a id="Choose_EquipmentKind">
    <evt aid="popupcall" type="WM_POPUP" id="Choose_EquipmentKind" src="/act/GPN/GateValvesMenuListPopup" args="" rets=""/>
  </a>
  <lay>
    <grid id="General">
      <row id="Point2" hide="yes">
      </row>
    </grid>
  </lay>
</wnd>
